pydantic_sql_bridge/__init__.py
pydantic_sql_bridge/pydantic_first.py
pydantic_sql_bridge/read_write.py
pydantic_sql_bridge/sql_first.py
pydantic_sql_bridge/utils.py
pydantic_sql_bridge-0.0.7.dist-info/LICENSE
pydantic_sql_bridge-0.0.7.dist-info/METADATA
pydantic_sql_bridge-0.0.7.dist-info/WHEEL
pydantic_sql_bridge-0.0.7.dist-info/RECORD
