Metadata-Version: 2.1
Name: pydantic-sql-bridge
Version: 0.0.7
Summary: A simple bridge between SQL databases and Pydantic
License: MIT
Author: Rik
Author-email: rik.de.kort@hey.com
Requires-Python: >=3.10,<4.0
Classifier: License :: OSI Approved :: MIT License
Classifier: Programming Language :: Python :: 3
Classifier: Programming Language :: Python :: 3.10
Classifier: Programming Language :: Python :: 3.11
Classifier: Programming Language :: Python :: 3.12
Requires-Dist: pggm-datalab-utils (>=2.11,<3.0)
Requires-Dist: pydantic (==2.*)
Requires-Dist: sqlglot (>=19.1,<20.0)
